logwrapper/__init__.py
logwrapper/logwrapper.py
logwrapper-0.1.7.dist-info/licenses/LICENSE
logwrapper-0.1.7.dist-info/METADATA
logwrapper-0.1.7.dist-info/WHEEL
logwrapper-0.1.7.dist-info/top_level.txt
logwrapper-0.1.7.dist-info/RECORD
