Metadata-Version: 2.4
Name: logwrapper
Version: 0.1.7
Summary: Python log wrapper
Home-page: https://github.com/YHYJ/LogWrapper
Author: YJ
Author-email: yj1516268@outlook.com
Project-URL: Bug Tracker, https://github.com/YHYJ/LogWrapper/issues
Classifier: Programming Language :: Python :: 3
Classifier: License :: OSI Approved :: GNU General Public License v3 (GPLv3)
Classifier: Operating System :: OS Independent
Requires-Python: >=3
License-File: LICENSE
Dynamic: license-file
